[
    {
        "question": "You frequently form new friendships.",
        "dimension": "E",
        "number": 1,
        "validated": "Yes"
    },
    {
        "question": "You're more thrilled by intricate and original concepts than by simple, straightforward ones.",
        "dimension": "N",
        "number": 2,
        "validated": "Yes"
    },
    {
        "question": "You tend to be convinced more by emotional resonance than by logical arguments.",
        "dimension": "F",
        "number": 3,
        "validated": "Yes"
    },
    {
        "question": "Your home and workspace are tidy and well-organized.",
        "dimension": "J",
        "number": 4,
        "validated": "Yes"
    },
    {
        "question": "The thought of networking or self-promotion to strangers feels very intimidating to you.",
        "dimension": "I",
        "number": 6,
        "validated": "Yes"
    },
    {
        "question": "You plan tasks efficiently and often finish them long before they're due.",
        "dimension": "J",
        "number": 7,
        "validated": "Yes"
    },
    {
        "question": "Personal narratives and emotions impact you more than statistics or data.",
        "dimension": "F",
        "number": 8,
        "validated": "Yes"
    },
    {
        "question": "You enjoy using organizational tools such as planners and checklists.",
        "dimension": "J",
        "number": 9,
        "validated": "Yes"
    },
    {
        "question": "You're at ease approaching someone interesting and starting a conversation.",
        "dimension": "E",
        "number": 11,
        "validated": "Yes"
    },
    {
        "question": "You're not particularly interested in debates about different interpretations of art or literature.",
        "dimension": "S",
        "number": 12,
        "validated": "Yes"
    },
    {
        "question": "When making decisions, you value facts more than people's emotions.",
        "dimension": "T",
        "number": 13,
        "validated": "Yes"
    },
    {
        "question": "You frequently let your day happen without any planned schedule.",
        "dimension": "P",
        "number": 14,
        "validated": "Yes"
    },
    {
        "question": "You take pleasure in engaging in group activities.",
        "dimension": "E",
        "number": 16,
        "validated": "Yes"
    },
    {
        "question": "You like trying out innovative and unproven methods.",
        "dimension": "N",
        "number": 17,
        "validated": "Yes"
    },
    {
        "question": "You value kindness over blunt honesty.",
        "dimension": "F",
        "number": 18,
        "validated": "Yes"
    },
    {
        "question": "You're eager to explore new experiences and learn about different fields.",
        "dimension": "N",
        "number": 19,
        "validated": "Yes"
    },
    {
        "question": "You prefer solitary hobbies and activities over group ones.",
        "dimension": "I",
        "number": 21,
        "validated": "Yes"
    },
    {
        "question": "Writing fiction professionally is something you can't envision for yourself.",
        "dimension": "S",
        "number": 22,
        "validated": "Yes"
    },
    {
        "question": "You prefer efficient decision-making, even if it overlooks emotional factors.",
        "dimension": "T",
        "number": 23,
        "validated": "Yes"
    },
    {
        "question": "You like to finish your chores before you relax.",
        "dimension": "J",
        "number": 24,
        "validated": "Yes"
    },
    {
        "question": "During arguments, you're more focused on being right than on sparing others' feelings.",
        "dimension": "T",
        "number": 25,
        "validated": "Yes"
    },
    {
        "question": "At social events, you typically wait for others to initiate introductions.",
        "dimension": "I",
        "number": 26,
        "validated": "Yes"
    },
    {
        "question": "Emotional appeals don't easily influence you.",
        "dimension": "T",
        "number": 28,
        "validated": "Yes"
    },
    {
        "question": "You frequently procrastinate until the last minute.",
        "dimension": "P",
        "number": 29,
        "validated": "Yes"
    },
    {
        "question": "You find pleasure in discussing moral dilemmas.",
        "dimension": "N",
        "number": 30,
        "validated": "Yes"
    },
    {
        "question": "You generally prefer company over being alone.",
        "dimension": "E",
        "number": 31,
        "validated": "Yes"
    },
    {
        "question": "Highly theoretical discussions tend to bore or lose your interest.",
        "dimension": "S",
        "number": 32,
        "validated": "Yes"
    },
    {
        "question": "If facts and feelings clash, you tend to follow your emotions.",
        "dimension": "F",
        "number": 33,
        "validated": "Yes"
    },
    {
        "question": "Maintaining a regular work or study routine is difficult for you.",
        "dimension": "P",
        "number": 34,
        "validated": "Yes"
    },
    {
        "question": "Your friends might say you're energetic and sociable.",
        "dimension": "E",
        "number": 36,
        "validated": "Yes"
    },
    {
        "question": "You're attracted to creative activities like writing.",
        "dimension": "N",
        "number": 37,
        "validated": "Yes"
    },
    {
        "question": "You tend to make decisions based on facts rather than feelings.",
        "dimension": "T",
        "number": 38,
        "validated": "Yes"
    },
    {
        "question": "You prefer having a daily checklist of tasks.",
        "dimension": "J",
        "number": 39,
        "validated": "Yes"
    },
    {
        "question": "You tend to avoid making phone calls.",
        "dimension": "I",
        "number": 41,
        "validated": "Yes"
    },
    {
        "question": "You like delving into new ideas and perspectives.",
        "dimension": "N",
        "number": 42,
        "validated": "Yes"
    },
    {
        "question": "You're able to quickly bond with new acquaintances.",
        "dimension": "E",
        "number": 43,
        "validated": "Yes"
    },
    {
        "question": "When plans are disrupted, your main goal is to return to them promptly.",
        "dimension": "J",
        "number": 44,
        "validated": "Yes"
    },
    {
        "question": "You're not particularly keen on speculating about future world scenarios.",
        "dimension": "S",
        "number": 46,
        "validated": "Yes"
    },
    {
        "question": "In decision-making, you consider people's feelings more than logic or efficiency.",
        "dimension": "F",
        "number": 48,
        "validated": "Yes"
    },
    {
        "question": "Your work style involves spontaneous energy rather than consistent organization.",
        "dimension": "P",
        "number": 49,
        "validated": "Yes"
    },
    {
        "question": "You'd prefer a job where you mostly work independently.",
        "dimension": "I",
        "number": 51,
        "validated": "Yes"
    },
    {
        "question": "You think contemplating abstract philosophical questions is pointless.",
        "dimension": "S",
        "number": 52,
        "validated": "Yes"
    },
    {
        "question": "You're more attracted to lively, bustling environments than to quiet ones.",
        "dimension": "E",
        "number": 53,
        "validated": "Yes"
    },
    {
        "question": "When a choice feels correct, you act on it without additional evidence.",
        "dimension": "F",
        "number": 54,
        "validated": "Yes"
    },
    {
        "question": "You finish tasks methodically, without skipping steps.",
        "dimension": "J",
        "number": 56,
        "validated": "Yes"
    },
    {
        "question": "You favor tasks that need creative problem-solving over those with set procedures.",
        "dimension": "N",
        "number": 57,
        "validated": "Yes"
    },
    {
        "question": "When deciding, you rely more on gut feelings than logical analysis.",
        "dimension": "F",
        "number": 58,
        "validated": "Yes"
    },
    {
        "question": "Deadlines are challenging for you to meet.",
        "dimension": "P",
        "number": 59,
        "validated": "Yes"
    }
]
